SigProfilerAssignment/Analyzer.py
SigProfilerAssignment/SigProfilerAssignment_CLI.py
SigProfilerAssignment/__init__.py
SigProfilerAssignment/decompose_subroutines.py
SigProfilerAssignment/decomposition.py
SigProfilerAssignment/single_sample.py
SigProfilerAssignment/version.py
SigProfilerAssignment/DecompositionPlots/PlotDecomposition.py
SigProfilerAssignment/DecompositionPlots/PlotDecomposition_CNV48.py
SigProfilerAssignment/DecompositionPlots/PlotDecomposition_DBS78.py
SigProfilerAssignment/DecompositionPlots/PlotDecomposition_ID83.py
SigProfilerAssignment/DecompositionPlots/PlotDecomposition_SBS1536.py
SigProfilerAssignment/DecompositionPlots/PlotDecomposition_SBS288.py
SigProfilerAssignment/DecompositionPlots/PlotDecomposition_SBS96.py
SigProfilerAssignment/DecompositionPlots/PlotDecomposition_SV32.py
SigProfilerAssignment/DecompositionPlots/SigProfilerPlottingMatrix.py
SigProfilerAssignment/DecompositionPlots/__init__.py
SigProfilerAssignment/DecompositionPlots/ExampleSample/CNV48_De-Novo_Signatures.txt
SigProfilerAssignment/DecompositionPlots/ExampleSample/COSMIC_CNV48_Signatures.txt
SigProfilerAssignment/DecompositionPlots/ExampleSample/COSMIC_DBS78_Signatures.txt
SigProfilerAssignment/DecompositionPlots/ExampleSample/COSMIC_ID83_Signatures.txt
SigProfilerAssignment/DecompositionPlots/ExampleSample/COSMIC_SBS288_Signatures.txt
SigProfilerAssignment/DecompositionPlots/ExampleSample/COSMIC_SV32_Signatures.txt
SigProfilerAssignment/DecompositionPlots/ExampleSample/De_Novo_Solution_Signatures_DINUC.txt
SigProfilerAssignment/DecompositionPlots/ExampleSample/De_Novo_Solution_Signatures_INDEL.txt
SigProfilerAssignment/DecompositionPlots/ExampleSample/De_Novo_Solution_Signatures_SBS1536.txt
SigProfilerAssignment/DecompositionPlots/ExampleSample/De_Novo_Solution_Signatures_SBS288.txt
SigProfilerAssignment/DecompositionPlots/ExampleSample/De_Novo_Solution_Signatures_SBS96.txt
sigprofilerassignment-1.1.3.dist-info/licenses/LICENSE.txt
sigprofilerassignment-1.1.3.dist-info/METADATA
sigprofilerassignment-1.1.3.dist-info/WHEEL
sigprofilerassignment-1.1.3.dist-info/entry_points.txt
sigprofilerassignment-1.1.3.dist-info/top_level.txt
sigprofilerassignment-1.1.3.dist-info/RECORD
