Metadata-Version: 2.4
Name: SigProfilerAssignment
Version: 1.1.3
Summary: Mutational signatures attribution and decomposition tool
Home-page: https://github.com/AlexandrovLab/SigProfilerAssignment.git
Author: Raviteja Vangara
Author-email: rvangara@health.ucsd.edu
License: UCSD
Requires-Python: >=3.9
License-File: LICENSE.txt
Requires-Dist: scipy>=1.13
Requires-Dist: numpy>=2.0.0
Requires-Dist: pandas>=2.0.0
Requires-Dist: SigProfilerMatrixGenerator>=1.3.0
Requires-Dist: sigProfilerPlotting>=1.4.0
Requires-Dist: reportlab>=3.5.42
Requires-Dist: pypdf>=6.0.0
Requires-Dist: alive_progress>=2.4.1
Requires-Dist: pdf2image>=1.16.0
Provides-Extra: tests
Requires-Dist: pytest; extra == "tests"
Dynamic: author
Dynamic: author-email
Dynamic: description
Dynamic: description-content-type
Dynamic: home-page
Dynamic: license
Dynamic: license-file
Dynamic: provides-extra
Dynamic: requires-dist
Dynamic: requires-python
Dynamic: summary
